async_runner/__init__.py
async_runner/core.py
divine_async_runner-0.1.7.dist-info/METADATA
divine_async_runner-0.1.7.dist-info/WHEEL
divine_async_runner-0.1.7.dist-info/licenses/LICENSE
divine_async_runner-0.1.7.dist-info/RECORD
