Metadata-Version: 2.4
Name: divine-async-runner
Version: 0.1.7
Summary: A unified async process runner with configurable output handling and robust error management.
Project-URL: Homepage, https://github.com/divinescreener/divine-async-runner
Project-URL: Issues, https://github.com/divinescreener/divine-async-runner/issues
Author-email: DIVINE <admin@divine.sh>
License: MIT
License-File: LICENSE
Requires-Python: >=3.13
Requires-Dist: anyio>=4.0.0
